{"box_data": [{"position": {"minX": 13.125, "minY": 596.25, "maxX": 98.0, "maxY": 671.75}, "class_id": 0, "box_caption": "bottle 0.889", "scores": {"class_score": 0.888671875}, "domain": "pixel"}, {"position": {"minX": 121.67330932617188, "minY": 553.4404907226562, "maxX": 190.82669067382812, "maxY": 610.5595092773438}, "class_id": 1, "box_caption": "cups 0.879", "scores": {"class_score": 0.87939453125}, "domain": "pixel"}, {"position": {"minX": 75.03266906738281, "minY": 651.3673706054688, "maxX": 228.4673309326172, "maxY": 789.6326293945312}, "class_id": 2, "box_caption": "drink-cans 0.872", "scores": {"class_score": 0.8720703125}, "domain": "pixel"}, {"position": {"minX": 19.15831756591797, "minY": 536.2532958984375, "maxX": 109.34168243408203, "maxY": 577.7467041015625}, "class_id": 2, "box_caption": "drink-cans 0.857", "scores": {"class_score": 0.85693359375}, "domain": "pixel"}, {"position": {"minX": 11.616580963134766, "minY": 561.1823120117188, "maxX": 43.695919036865234, "maxY": 605.8176879882812}, "class_id": 0, "box_caption": "bottle 0.096", "scores": {"class_score": 0.09625244140625}, "domain": "pixel"}, {"position": {"minX": 13.053717613220215, "minY": 562.8554077148438, "maxX": 37.50878143310547, "maxY": 600.1445922851562}, "class_id": 2, "box_caption": "drink-cans 0.082", "scores": {"class_score": 0.08172607421875}, "domain": "pixel"}, {"position": {"minX": 21.58328628540039, "minY": 535.5797729492188, "maxX": 108.41671752929688, "maxY": 578.4202270507812}, "class_id": 0, "box_caption": "bottle 0.031", "scores": {"class_score": 0.0305328369140625}, "domain": "pixel"}], "class_labels": {"0": "bottle", "1": "cups", "2": "drink-cans", "3": "drink-packets", "4": "styrofoam", "5": "wrappers"}}